hide_key/HideKey.py
hide_key/__init__.py
hide_key-0.1.0.dist-info/METADATA
hide_key-0.1.0.dist-info/WHEEL
hide_key-0.1.0.dist-info/top_level.txt
hide_key-0.1.0.dist-info/RECORD
