Metadata-Version: 2.1
Name: hide-key
Version: 0.1.0
Summary: simple library for Data Engineering
Home-page: https://medium-multiply.readthedocs.io/
Author: Ziren Xia
Author-email: zx1141@nyu.edu
License: MIT
Classifier: Intended Audience :: Developers
Classifier: License :: OSI Approved :: MIT License
Classifier: Programming Language :: Python
Classifier: Programming Language :: Python :: 3
Classifier: Programming Language :: Python :: 3.6
Classifier: Programming Language :: Python :: 3.7
Classifier: Programming Language :: Python :: 3.8
Classifier: Programming Language :: Python :: 3.9
Classifier: Operating System :: OS Independent
